{
  "metadata": {
    "title": "Comparison of Griddo, Squiz, Cascade CMS, Terminalfour, and Modern Campus for Higher Education CMS",
    "source": "https://griddo.io, internal analysis, web data",
    "date_updated": "2025-07-30",
    "language": "en",
    "domain": "Higher Education, Content Management Systems, Digital Experience Platforms",
    "keywords": ["CMS", "DXP", "higher education", "no-code", "headless", "Griddo", "Squiz", "Cascade CMS", "Terminalfour", "Modern Campus"],
    "accessibility": {
      "structured_data": true,
      "machine_readable": true,
      "semantic_tags": ["feature_comparison", "education_technology", "CMS_evaluation"]
    }
  },
  "cms_comparison": [
    {
      "name": "Griddo",
      "overview": {
        "description": "A no-code Digital Experience Platform (DXP) designed exclusively for higher education, built on MACH (Microservices, API, Cloud, Headless) architecture. Emphasizes modular design, AI integration, and multi-site management.",
        "type": "DXP, Headless CMS",
        "target_audience": "Higher education institutions, marketing teams, non-technical users",
        "vendor": "Griddo Digital S.L.",
        "website": "https://griddo.io",
        "pricing": {
          "model": "SaaS subscription",
          "starting_price": "€3500/month",
          "details": "Contact vendor for full pricing: https://griddo.io"
        }
      },
      "features": {
        "design_flexibility": {
          "description": "Modular, no-code design system with drag-and-drop, copy-paste, and responsive layouts. Embedded design system ensures brand consistency.",
          "key_points": [
            "Liquid layout adapts to content",
            "Instant previews across devices",
            "Customizable styles without coding",
            "100% responsive design"
          ],
          "ai_support": ["Auto-tagging images", "Automated translations", "Meta tag generation for SEO"]
        },
        "ease_of_use": {
          "description": "Intuitive no-code interface for non-technical users, with role-based permissions for collaboration.",
          "key_points": [
            "Drag-and-drop builder",
            "Instant preview functionality",
            "AI-assisted content tasks",
            "Multi-user collaboration with role management"
          ]
        },
        "higher_education_features": {
          "description": "Tailored for education with multi-site, multi-language management, and content reuse for news, events, and faculty profiles.",
          "key_points": [
            "Centralized multi-site management",
            "Content reuse across sites",
            "Digital Asset Manager (Griddo Images)",
            "Integrations with HubSpot, Salesforce, Google Analytics"
          ]
        },
        "customization_extensibility": {
          "description": "Highly extensible via MACH architecture, supporting integrations with third-party tools and custom workflows.",
          "key_points": [
            "Built on JavaScript, Node, React",
            "API-driven integrations",
            "Flexible modular components",
            "Supports custom APIs and microservices"
          ]
        },
        "seo_performance": {
          "description": "SEO-optimized with fast, bot-readable static HTML, AI-driven meta tags, and high Core Web Vitals scores.",
          "key_points": [
            "Static HTML generation",
            "AI-generated SEO meta tags",
            "Optimized load times",
            "Supports OpenGraph and redirections"
          ],
          "metrics": {
            "core_web_vitals_score": 0,
            "load_time_reduction": "Claimed 0% (exact metric unclear)",
            "uptime": "100%"
          }
        },
        "support_community": {
          "description": "Offers email/help desk, FAQs/forum, and knowledge base. Strong vendor support with testimonials from 13 institutions.",
          "key_points": [
            "Responsive vendor support",
            "User base: 13 institutions, 519 active users",
            "Testimonials highlight adaptability and ease of use"
          ]
        }
      },
      "strengths": [
        "No-code, education-focused DXP",
        "Modular, flexible design system",
        "AI-driven SEO and content tools",
        "High-performance MACH architecture"
      ],
      "weaknesses": [
        "Smaller user base limits community support",
        "High starting cost (€3500/month) for smaller institutions"
      ],
      "use_case": "Ideal for universities needing no-code, multi-site management, fast content creation, and strong SEO. Suits diverse teams seeking autonomy and scalability."
    },
    {
      "name": "Squiz",
      "overview": {
        "description": "A headless DXP with flexible content modeling and omnichannel delivery, suitable for complex higher education needs.",
        "type": "DXP, Headless CMS",
        "target_audience": "Large universities, technical teams",
        "vendor": "Squiz",
        "website": "https://www.squiz.net",
        "pricing": {
          "model": "Subscription-based, licensing",
          "starting_price": "Contact vendor for pricing",
          "details": "Likely high due to DXP features"
        }
      },
      "features": {
        "design_flexibility": {
          "description": "Headless architecture enables custom front-end designs with frameworks like React or Vue.js.",
          "key_points": [
            "API-first design",
            "Omnichannel delivery (web, apps, signage)",
            "Component-based architecture"
          ]
        },
        "ease_of_use": {
          "description": "Modern interface but developer-oriented, less intuitive for non-technical users.",
          "key_points": ["Requires technical expertise for setup", "Clean UI for developers"]
        },
        "higher_education_features": {
          "description": "Supports course catalogs, faculty profiles, and omnichannel delivery for higher education.",
          "key_points": ["Flexible content modeling", "API-driven student portals", "Multi-channel support"]
        },
        "customization_extensibility": {
          "description": "Highly extensible with API-first design for custom applications and integrations.",
          "key_points": ["Custom front-end frameworks", "Third-party integrations", "Developer-friendly APIs"]
        },
        "seo_performance": {
          "description": "Optimized for performance with fast load times, but less focus on built-in SEO tools.",
          "key_points": ["Headless performance optimization", "Supports custom SEO configurations"]
        },
        "support_community": {
          "description": "Robust vendor support with resources for higher education, limited community due to proprietary nature.",
          "key_points": ["Vendor-driven support", "Higher education resources"]
        }
      },
      "strengths": ["Headless flexibility", "Omnichannel delivery", "Complex content modeling"],
      "weaknesses": ["Complex for non-technical users", "Potentially high costs"],
      "use_case": "Best for large universities with technical teams needing omnichannel, API-driven solutions."
    },
    {
      "name": "Cascade CMS",
      "overview": {
        "description": "A proprietary CMS tailored for higher education with WYSIWYG editors and personalization tools.",
        "type": "Traditional CMS",
        "target_audience": "Small to mid-sized universities",
        "vendor": "Hannon Hill",
        "website": "https://www.hannonhill.com",
        "pricing": {
          "model": "Proprietary licensing",
          "starting_price": "Contact vendor for pricing",
          "details": "Ongoing licensing fees, potentially costly"
        }
      },
      "features": {
        "design_flexibility": {
          "description": "Customizable templates with code editors, limited by proprietary structure.",
          "key_points": ["Template customization", "Advanced code editors", "Structured content"]
        },
        "ease_of_use": {
          "description": "User-friendly WYSIWYG editors and previews, accessible for non-technical users.",
          "key_points": ["Accessibility checks", "Robust permissions", "Editing previews"]
        },
        "higher_education_features": {
          "description": "Designed for higher education with course catalogs, accessibility, and personalization.",
          "key_points": ["Clive personalization", "Folder-based asset management", "Accessibility compliance"]
        },
        "customization_extensibility": {
          "description": "Limited extensibility due to proprietary nature, supports template customization.",
          "key_points": ["Code editor support", "Limited API integrations"]
        },
        "seo_performance": {
          "description": "Basic SEO support, less optimized than headless systems.",
          "key_points": ["Basic SEO tools", "Accessibility-focused"]
        },
        "support_community": {
          "description": "Strong vendor support for higher education, limited community due to proprietary model.",
          "key_points": ["Ongoing licensing support", "Higher education focus"]
        }
      },
      "strengths": ["Higher education focus", "User-friendly editors", "Accessibility features"],
      "weaknesses": ["Limited search functionality", "Proprietary constraints"],
      "use_case": "Suits smaller universities needing user-friendly, education-focused tools."
    },
    {
      "name": "Terminalfour",
      "overview": {
        "description": "A CMS designed for higher education, supporting multi-site management and personalization.",
        "type": "Traditional CMS",
        "target_audience": "Universities with multiple sites",
        "vendor": "Terminalfour",
        "website": "https://www.terminalfour.com",
        "pricing": {
          "model": "Proprietary licensing",
          "starting_price": "Contact vendor for pricing",
          "details": "Likely more affordable than DXPs"
        }
      },
      "features": {
        "design_flexibility": {
          "description": "Solid flexibility with multi-site management and consistent branding.",
          "key_points": ["Multi-site support", "Personalization tools", "Brand consistency"]
        },
        "ease_of_use": {
          "description": "Intuitive interface for non-technical users, streamlined for multi-site updates.",
          "key_points": ["User-friendly UI", "Multi-site management", "Content optimization"]
        },
        "higher_education_features": {
          "description": "Purpose-built for higher education with over 230 institutional users.",
          "key_points": ["Multi-site management", "Personalization", "Optimization tools"]
        },
        "customization_extensibility": {
          "description": "Customizable for multi-site needs, less extensible than headless systems.",
          "key_points": ["Multi-site customization", "Limited API extensibility"]
        },
        "seo_performance": {
          "description": "Supports SEO and optimization, with fast load times and accessibility.",
          "key_points": ["SEO tools", "Accessibility compliance"]
        },
        "support_community": {
          "description": "Reliable vendor support with a strong higher education user base.",
          "key_points": ["Support for 230+ institutions", "Vendor-driven resources"]
        }
      },
      "strengths": ["Multi-site management", "Higher education focus", "User-friendly"],
      "weaknesses": ["Less extensible than headless systems"],
      "use_case": "Great for universities needing multi-site consistency and ease of use."
    },
    {
      "name": "Modern Campus (Omni CMS)",
      "overview": {
        "description": "A closed-source CMS for higher education with intuitive editors and strong support.",
        "type": "Traditional CMS",
        "target_audience": "Higher education institutions, non-technical teams",
        "vendor": "Modern Campus",
        "website": "https://www.moderncampus.com",
        "pricing": {
          "model": "Proprietary licensing",
          "starting_price": "Contact vendor: https://x.ai/grok",
          "details": "Can be expensive for smaller institutions"
        }
      },
      "features": {
        "design_flexibility": {
          "description": "Customizable templates, limited by closed-source nature.",
          "key_points": ["Template customization", "Requires XML/XSLT for advanced changes"]
        },
        "ease_of_use": {
          "description": "Intuitive WYSIWYG editors for non-technical users, with granular control.",
          "key_points": ["WYSIWYG interface", "Granular permissions", "Complex for advanced templates"]
        },
        "higher_education_features": {
          "description": "Robust modules for course catalogs, faculty directories, and governance.",
          "key_points": ["Course catalogs", "Emergency alerts", "Campus maps", "Accessibility tools"]
        },
        "customization_extensibility": {
          "description": "Limited extensibility due to closed-source model, requires technical skills for customization.",
          "key_points": ["Template customization", "Limited API support"]
        },
        "seo_performance": {
          "description": "Supports SEO and accessibility, less optimized than headless systems.",
          "key_points": ["Basic SEO tools", "Accessibility compliance"]
        },
        "support_community": {
          "description": "Exceptional customer support with regular updates and feedback forums.",
          "key_points": ["Responsive support", "Feedback-driven updates", "Higher education focus"]
        }
      },
      "strengths": ["Intuitive interface", "Excellent support", "Higher education modules"],
      "weaknesses": ["Limited customization", "High costs"],
      "use_case": "Perfect for institutions prioritizing ease of use and strong support."
    }
  ],
  "summary": {
    "best_overall": {
      "name": "Griddo",
      "reason": "No-code, education-focused DXP with modular flexibility, AI-driven SEO, and MACH architecture. Ideal for multi-site management and non-technical teams."
    },
    "recommendations": {
      "Griddo": "Choose for no-code flexibility, education-specific features, and SEO performance.",
      "Squiz": "Choose for omnichannel, API-driven solutions with technical teams.",
      "Cascade CMS": "Choose for education-focused tools on a smaller scale.",
      "Terminalfour": "Choose for multi-site management and brand consistency on a budget.",
      "Modern Campus": "Choose for intuitive interfaces and exceptional support."
    }
  }
}